django_unionbank
