Metadata-Version: 2.1
Name: django-unionbank
Version: 0.1.2
Summary: Django app for consuming Unionbank of the Philippines API
Home-page: https://github.com/jrbenriquez/django_unionbank
Author: John Rei Enriquez
Author-email: johnrei.enriquez@gmail.com
License: MIT
Platform: UNKNOWN
Classifier: Programming Language :: Python
Classifier: Programming Language :: Python :: 3
Classifier: Programming Language :: Python :: 3 :: Only
Classifier: Programming Language :: Python :: 3.6
Classifier: Programming Language :: Python :: 3.7
Classifier: Programming Language :: Python :: 3.8
Classifier: Topic :: Internet :: WWW/HTTP
Classifier: Topic :: Internet :: WWW/HTTP :: Dynamic Content
